esuls/__init__.py
esuls/db_cli.py
esuls/download_icon.py
esuls/request_cli.py
esuls/utils.py
esuls/tests/test_db_concurrent.py
esuls-0.1.14.dist-info/licenses/LICENSE
esuls-0.1.14.dist-info/METADATA
esuls-0.1.14.dist-info/WHEEL
esuls-0.1.14.dist-info/top_level.txt
esuls-0.1.14.dist-info/RECORD
