Metadata-Version: 2.4
Name: esuls
Version: 0.1.14
Summary: Utility library for async database operations, HTTP requests, and parallel execution
Author-email: IperGiove <ipergiove@gmail.com>
License: MIT
Project-URL: Homepage, https://github.com/ipergiove/esuls
Project-URL: Repository, https://github.com/ipergiove/esuls
Classifier: Programming Language :: Python :: 3
Classifier: License :: OSI Approved :: MIT License
Classifier: Operating System :: OS Independent
Requires-Python: >=3.14
License-File: LICENSE
Requires-Dist: aiosqlite>=0.21.0
Requires-Dist: curl-cffi>=0.13.0
Requires-Dist: fake-useragent>=2.2.0
Requires-Dist: httpx[http2]>=0.28.1
Requires-Dist: loguru>=0.7.3
Requires-Dist: pillow>=12.0.0
Requires-Dist: python-magic>=0.4.27
Dynamic: license-file
